LICENSE
MANIFEST.in
README.md
package.json
setup.py
dash_coreui_components/AppAsideToggler.py
dash_coreui_components/AppBreadcrumb.py
dash_coreui_components/AppCard.py
dash_coreui_components/AppFooter.py
dash_coreui_components/AppHeader.py
dash_coreui_components/AppHeaderDropdown.py
dash_coreui_components/AppNavbarBrand.py
dash_coreui_components/AppRouteConditional.py
dash_coreui_components/AppSidebar.py
dash_coreui_components/AppSidebarFooter.py
dash_coreui_components/AppSidebarForm.py
dash_coreui_components/AppSidebarHeader.py
dash_coreui_components/AppSidebarNav.py
dash_coreui_components/AppSidebarToggler.py
dash_coreui_components/AppTableBody.py
dash_coreui_components/AppTableHeader.py
dash_coreui_components/__init__.py
dash_coreui_components/_imports_.py
dash_coreui_components/dash_coreui_components.min.js
dash_coreui_components/dash_coreui_components.min.js.map
dash_coreui_components/metadata.json
dash_coreui_components/package-info.json
dash_coreui_components.egg-info/PKG-INFO
dash_coreui_components.egg-info/SOURCES.txt
dash_coreui_components.egg-info/dependency_links.txt
dash_coreui_components.egg-info/top_level.txt