Metadata-Version: 1.0
Name: dash-coreui-components
Version: 0.1.0
Summary: CoreUI components for Plotly Dash
Home-page: UNKNOWN
Author: The QCArchive Developers <qcarchive@molssi.org>
Author-email: UNKNOWN
License: BSD-3-Clause
Platform: UNKNOWN
